vigilant/__init__.py
vigilant/__version__.py
vigilant/board.py
vigilant/dice.py
vigilant/game.py
vigilant/player.py
vigilant/property_list.json
vigilant_engine-0.1.0.dist-info/METADATA
vigilant_engine-0.1.0.dist-info/WHEEL
vigilant_engine-0.1.0.dist-info/top_level.txt
vigilant_engine-0.1.0.dist-info/RECORD
